{
    "settlements": [
        {
            "name": "Seaforth",
            "position": {
                "x": -517.0,
                "y": 20.996337890625,
                "z": 199.0
            },
            "provinceName": "",
            "province": {
                "instanceID": 0
            },
            "model": "FortressLevel3",
            "orientation": -34.0,
            "buildings": [],
            "population": 0,
            "happiness": 0.0,
            "food": 0.0
        },
        {
            "name": "Esum",
            "position": {
                "x": -687.0,
                "y": 20.996337890625,
                "z": 164.0
            },
            "provinceName": "",
            "province": {
                "instanceID": 0
            },
            "model": "FortressLevel3",
            "orientation": 60.0,
            "buildings": [],
            "population": 0,
            "happiness": 0.0,
            "food": 0.0
        },
        {
            "name": "Anlaard",
            "position": {
                "x": -462.0,
                "y": 20.996337890625,
                "z": 172.0
            },
            "provinceName": "",
            "province": {
                "instanceID": 0
            },
            "model": "FortressLevel3",
            "orientation": 20.0,
            "buildings": [],
            "population": 0,
            "happiness": 0.0,
            "food": 0.0
        },
        {
            "name": "Stumzart",
            "position": {
                "x": -377.0,
                "y": 20.996337890625,
                "z": 422.0
            },
            "provinceName": "",
            "province": {
                "instanceID": 0
            },
            "model": "FortressLevel3",
            "orientation": 84.0,
            "buildings": [],
            "population": 0,
            "happiness": 0.0,
            "food": 0.0
        }
    ]
}